README.rst
setup.py
src/moddy/__init__.py
src/moddy/constants.py
src/moddy/dot_fsm.py
src/moddy/dot_structure.py
src/moddy/fsm.py
src/moddy/fsm_part.py
src/moddy/interactive_sequence_diagram.py
src/moddy/sim_base.py
src/moddy/sim_core.py
src/moddy/sim_monitor.py
src/moddy/sim_part.py
src/moddy/sim_parts_mgr.py
src/moddy/sim_ports.py
src/moddy/sim_trace.py
src/moddy/sim_var_watch.py
src/moddy/trace_to_csv.py
src/moddy/utils.py
src/moddy/version.py
src/moddy/vt_sched_rtos.py
src/moddy/vthread.py
src/moddy.egg-info/PKG-INFO
src/moddy.egg-info/SOURCES.txt
src/moddy.egg-info/dependency_links.txt
src/moddy.egg-info/requires.txt
src/moddy.egg-info/top_level.txt
src/moddy/lib/__init__.py
src/moddy/lib/pdu.py
src/moddy/lib/trace_search.py
src/moddy/lib/net/__init__.py
src/moddy/lib/net/eth_unmanaged_switch.py
src/moddy/lib/net/ethernet.py
src/moddy/seq_diag_interactive_viewer/__init__.py
src/moddy/seq_diag_interactive_viewer/seq_diag_interactive_viewer.css
src/moddy/seq_diag_interactive_viewer/seq_diag_interactive_viewer.js