Metadata-Version: 1.0
Name: moddy
Version: 2.0.0
Summary: A discrete event simulator generating sequence diagrams
Home-page: https://github.com/KlausPopp/Moddy
Author: Klaus Popp
Author-email: klauspopp@gmx.de
License: LGPL-3.0
Project-URL: Documentation, https://klauspopp.github.io/Moddy/
Project-URL: Source Code, https://github.com/KlausPopp/Moddy/
Keywords: simulation modelling
Platform: OS Independent
